jstree.py
setup.py
jstree.egg-info/PKG-INFO
jstree.egg-info/SOURCES.txt
jstree.egg-info/dependency_links.txt
jstree.egg-info/requires.txt
jstree.egg-info/top_level.txt