Metadata-Version: 1.1
Name: jstree
Version: 0.1.2
Summary: A package that helps generate JSON data for jQuery jsTree.
Home-page: https://github.com/grimwm/py-jstree
Author: William Grim
Author-email: william@grimapps.com
License: UNKNOWN
Platform: UNKNOWN
Classifier: Development Status :: 2 - Pre-Alpha
Classifier: License :: OSI Approved :: Apache Software License
Classifier: Operating System :: OS Independent
Classifier: Programming Language :: Python
Classifier: Topic :: Software Development :: Libraries :: Python Modules
